gsmtpd
