Metadata-Version: 1.1
Name: gsmtpd
Version: 0.1.9.3
Summary: A smtpd server impletement based on Gevent
Home-page: https://github.com/34nm/gsmtpd
Author: Meng Zhuo
Author-email: mengzhuo1203@gmail.com
License: MIT
Platform: any
Classifier: License :: OSI Approved :: MIT License
Classifier: Programming Language :: Python :: 2
Classifier: Programming Language :: Python :: 2.6
Classifier: Programming Language :: Python :: 2.7
Classifier: Topic :: Communications :: Email :: Mail Transport Agents
Classifier: Topic :: Communications :: Email
